dikshant/__init__.py
dikshant/assistant.py
dikshant/cli.py
dikshant/core/__init__.py
dikshant/core/command_processor.py
dikshant/core/system_controller.py
dikshant/core/text_to_speech.py
dikshant/core/voice_recognizer.py
dikshant/data/commands.json
dikshant-0.2.4.dist-info/licenses/LICENSE.txt
dikshant-0.2.4.dist-info/METADATA
dikshant-0.2.4.dist-info/WHEEL
dikshant-0.2.4.dist-info/entry_points.txt
dikshant-0.2.4.dist-info/top_level.txt
dikshant-0.2.4.dist-info/RECORD
