Metadata-Version: 2.4
Name: dikshant
Version: 0.2.4
Summary: Voice-activated Windows assistant that performs tasks based on speech commands starting with 'hey friend'.
Author-email: Dikshant Ghimire <dikkughimire@gmail.com>
License: MIT
Project-URL: Homepage, https://github.com/dikshantgh/dikshant
Project-URL: Repository, https://github.com/dikshantgh/dikshant
Project-URL: Issues, https://github.com/dikshantgh/dikshant/issues
Classifier: Development Status :: 4 - Beta
Classifier: Environment :: Console
Classifier: Intended Audience :: End Users/Desktop
Classifier: Topic :: Utilities
Classifier: Topic :: Multimedia :: Sound/Audio :: Speech
Classifier: License :: OSI Approved :: MIT License
Classifier: Operating System :: Microsoft :: Windows
Classifier: Programming Language :: Python :: 3
Requires-Python: >=3.7
License-File: LICENSE.txt
Requires-Dist: speechrecognition>=3.8
Requires-Dist: pyttsx3>=2.90
Requires-Dist: pyaudio>=0.2.11
Requires-Dist: pyautogui>=0.9.53
Dynamic: license-file
